fsmlite/__init__.py
fsmlite/fsm.py
fsmlite-0.1.1.dist-info/METADATA
fsmlite-0.1.1.dist-info/WHEEL
fsmlite-0.1.1.dist-info/licenses/LICENSE
fsmlite-0.1.1.dist-info/RECORD
