Metadata-Version: 2.4
Name: fsmlite
Version: 0.1.1
Summary: A lightweight finite state machine library
Project-URL: Homepage, https://github.com/c4pt0r/fsmlite
Author-email: dongxu <i@huangdx.net>
Maintainer-email: dongxu <i@huangdx.net>
License:                                  Apache License
License-File: LICENSE
Keywords: finite-state-machine,fsm,state-machine
Classifier: Development Status :: 3 - Alpha
Classifier: Intended Audience :: Developers
Classifier: License :: OSI Approved :: MIT License
Classifier: Operating System :: OS Independent
Classifier: Programming Language :: Python :: 3
Classifier: Programming Language :: Python :: 3.10
Classifier: Programming Language :: Python :: 3.11
Classifier: Programming Language :: Python :: 3.12
Classifier: Topic :: Software Development :: Libraries :: Python Modules
Requires-Python: >=3.10
